{
  "75 benefits": {
    "name": "75 Benefits",
    "source": "builtin",
    "ats": "unknown",
    "slug": "75benefits"
  },
  "hiring now": {
    "name": "Hiring Now",
    "source": "builtin",
    "ats": "unknown",
    "slug": "hiringnow"
  },
  "65 benefits": {
    "name": "65 Benefits",
    "source": "builtin",
    "ats": "unknown",
    "slug": "65benefits"
  },
  "55 benefits": {
    "name": "55 Benefits",
    "source": "builtin",
    "ats": "unknown",
    "slug": "55benefits"
  },
  "see our teams": {
    "name": "See Our Teams",
    "source": "builtin",
    "ats": "unknown",
    "slug": "seeourteams"
  },
  "69 benefits": {
    "name": "69 Benefits",
    "source": "builtin",
    "ats": "unknown",
    "slug": "69benefits"
  },
  "66 benefits": {
    "name": "66 Benefits",
    "source": "builtin",
    "ats": "unknown",
    "slug": "66benefits"
  },
  "48 benefits": {
    "name": "48 Benefits",
    "source": "builtin",
    "ats": "unknown",
    "slug": "48benefits"
  },
  "47 benefits": {
    "name": "47 Benefits",
    "source": "builtin",
    "ats": "unknown",
    "slug": "47benefits"
  },
  "46 benefits": {
    "name": "46 Benefits",
    "source": "builtin",
    "ats": "unknown",
    "slug": "46benefits"
  },
  "91 benefits": {
    "name": "91 Benefits",
    "source": "builtin",
    "ats": "unknown",
    "slug": "91benefits"
  },
  "77 benefits": {
    "name": "77 Benefits",
    "source": "builtin",
    "ats": "unknown",
    "slug": "77benefits"
  },
  "43 benefits": {
    "name": "43 Benefits",
    "source": "builtin",
    "ats": "unknown",
    "slug": "43benefits"
  },
  "59 benefits": {
    "name": "59 Benefits",
    "source": "builtin",
    "ats": "unknown",
    "slug": "59benefits"
  },
  "68 benefits": {
    "name": "68 Benefits",
    "source": "builtin",
    "ats": "unknown",
    "slug": "68benefits"
  },
  "51 benefits": {
    "name": "51 Benefits",
    "source": "builtin",
    "ats": "unknown",
    "slug": "51benefits"
  },
  "95 benefits": {
    "name": "95 Benefits",
    "source": "builtin",
    "ats": "unknown",
    "slug": "95benefits"
  },
  "56 benefits": {
    "name": "56 Benefits",
    "source": "builtin",
    "ats": "unknown",
    "slug": "56benefits"
  },
  "105 benefits": {
    "name": "105 Benefits",
    "source": "builtin",
    "ats": "unknown",
    "slug": "105benefits"
  },
  "99 benefits": {
    "name": "99 Benefits",
    "source": "builtin",
    "ats": "unknown",
    "slug": "99benefits"
  }
}